RPi_GPIO_Helper/__init__.py
rpi_gpio_helper-2.3.0.dist-info/METADATA
rpi_gpio_helper-2.3.0.dist-info/WHEEL
rpi_gpio_helper-2.3.0.dist-info/licenses/LICENSE
rpi_gpio_helper-2.3.0.dist-info/RECORD
