Metadata-Version: 2.1
Name: RPi_GPIO_Helper
Version: 2.3.0
Summary: RPi.GPIO Helper Library.
Project-URL: Homepage, https://github.com/taogya/RPi_GPIO_Helper
Project-URL: Bug Tracker, https://github.com/taogya/RPi_GPIO_Helper/issues
Author-email: Taogya <132679709+taogya@users.noreply.github.com>
License: BSD 3-Clause License
License-File: LICENSE
Classifier: License :: OSI Approved :: BSD License
Classifier: Operating System :: POSIX :: Linux
Classifier: Programming Language :: Python :: 3
Requires-Python: >=3.9
